eth_rlp/__init__.py
eth_rlp/main.py
eth_rlp/py.typed
eth_rlp-2.1.0.dist-info/LICENSE
eth_rlp-2.1.0.dist-info/METADATA
eth_rlp-2.1.0.dist-info/WHEEL
eth_rlp-2.1.0.dist-info/top_level.txt
eth_rlp-2.1.0.dist-info/RECORD
