Metadata-Version: 2.1
Name: eth-rlp
Version: 2.1.0
Summary: eth-rlp: RLP definitions for common Ethereum objects in Python
Home-page: https://github.com/ethereum/eth-rlp
Author: The Ethereum Foundation
Author-email: snakecharmers@ethereum.org
License: MIT
Keywords: ethereum
Classifier: Development Status :: 5 - Production/Stable
Classifier: Intended Audience :: Developers
Classifier: License :: OSI Approved :: MIT License
Classifier: Natural Language :: English
Classifier: Programming Language :: Python :: 3
Classifier: Programming Language :: Python :: 3.8
Classifier: Programming Language :: Python :: 3.9
Classifier: Programming Language :: Python :: 3.10
Classifier: Programming Language :: Python :: 3.11
Classifier: Programming Language :: Python :: 3.12
Requires-Python: >=3.8, <4
License-File: LICENSE
Requires-Dist: eth-utils>=2.0.0
Requires-Dist: hexbytes>=1.2.0
Requires-Dist: rlp>=0.6.0
Requires-Dist: typing_extensions>=4.0.1; python_version <= "3.10"
Provides-Extra: dev
Requires-Dist: build>=0.9.0; extra == "dev"
Requires-Dist: bumpversion>=0.5.3; extra == "dev"
Requires-Dist: ipython; extra == "dev"
Requires-Dist: pre-commit>=3.4.0; extra == "dev"
Requires-Dist: tox>=4.0.0; extra == "dev"
Requires-Dist: twine; extra == "dev"
Requires-Dist: wheel; extra == "dev"
Requires-Dist: sphinx>=6.0.0; extra == "dev"
Requires-Dist: sphinx_rtd_theme>=1.0.0; extra == "dev"
Requires-Dist: towncrier<22,>=21; extra == "dev"
Requires-Dist: eth-hash[pycryptodome]; extra == "dev"
Requires-Dist: pytest>=7.0.0; extra == "dev"
Requires-Dist: pytest-xdist>=2.4.0; extra == "dev"
Provides-Extra: docs
Requires-Dist: sphinx>=6.0.0; extra == "docs"
Requires-Dist: sphinx_rtd_theme>=1.0.0; extra == "docs"
Requires-Dist: towncrier<22,>=21; extra == "docs"
Provides-Extra: test
Requires-Dist: eth-hash[pycryptodome]; extra == "test"
Requires-Dist: pytest>=7.0.0; extra == "test"
Requires-Dist: pytest-xdist>=2.4.0; extra == "test"
